accphys/.ipynb_checkpoints/__init__-checkpoint.py
accphys/.ipynb_checkpoints/adbooster-checkpoint.py
accphys/.ipynb_checkpoints/beamline-checkpoint.py
accphys/.ipynb_checkpoints/convert-checkpoint.py
accphys/.ipynb_checkpoints/elements-checkpoint.py
accphys/.ipynb_checkpoints/knob-checkpoint.py
accphys/.ipynb_checkpoints/nf-checkpoint.py
accphys/.ipynb_checkpoints/tools-checkpoint.py
accphys/__init__.py
accphys/adbooster.py
accphys/beamline.py
accphys/da-Copy1.py
accphys/elements/.ipynb_checkpoints/__init__-checkpoint.py
accphys/elements/.ipynb_checkpoints/cfm-checkpoint.py
accphys/elements/.ipynb_checkpoints/common-checkpoint.py
accphys/elements/.ipynb_checkpoints/poleface-checkpoint.py
accphys/elements/__init__.py
accphys/elements/cfm.py
accphys/elements/common.py
accphys/elements/drift.py
accphys/elements/phaserot.py
accphys/elements/poleface.py
accphys/elements/rfcavity.py
accphys/io/.ipynb_checkpoints/__init__-checkpoint.py
accphys/io/.ipynb_checkpoints/convert-checkpoint.py
accphys/io/.ipynb_checkpoints/from_madx-checkpoint.py
accphys/io/.ipynb_checkpoints/from_madx_old-checkpoint.py
accphys/io/.ipynb_checkpoints/from_pandas-checkpoint.py
accphys/io/__init__.py
accphys/io/convert.py
accphys/io/from_madx.py
accphys/knob.py
accphys/nf.py
accphys/plotting.py
accphys/tools.py
accphys-0.1.1.dist-info/LICENSE
accphys-0.1.1.dist-info/WHEEL
accphys-0.1.1.dist-info/METADATA
accphys-0.1.1.dist-info/RECORD
