Metadata-Version: 2.1
Name: accphys
Version: 0.1.1
Summary: Analyze non-linear single-particle storage ring dynamics
License: GPL v3
Author: Malte Titze
Author-email: mtitze@users.noreply.github.com
Requires-Python: >=3.8,<3.11
Classifier: License :: Other/Proprietary License
Classifier: Programming Language :: Python :: 3
Classifier: Programming Language :: Python :: 3.10
Classifier: Programming Language :: Python :: 3.8
Classifier: Programming Language :: Python :: 3.9
Requires-Dist: cpymad (>=1.10.0)
Requires-Dist: ipykernel (>=5.5.5,<6.0.0)
Requires-Dist: lieops (>=0.1.1,<0.2.0)
Requires-Dist: scipy (>=1.8.0,<2.0.0)
Requires-Dist: tqdm (>=4.64.0,<5.0.0)
